discord/ext/voice_recv/__init__.py
discord/ext/voice_recv/buffer.py
discord/ext/voice_recv/enums.py
discord/ext/voice_recv/gateway.py
discord/ext/voice_recv/opus.py
discord/ext/voice_recv/reader.py
discord/ext/voice_recv/router.py
discord/ext/voice_recv/rtp.py
discord/ext/voice_recv/silence.py
discord/ext/voice_recv/sinks.py
discord/ext/voice_recv/types.py
discord/ext/voice_recv/utils.py
discord/ext/voice_recv/video.py
discord/ext/voice_recv/voice_client.py
discord/ext/voice_recv/extras/__init__.py
discord/ext/voice_recv/extras/localplayback.py
discord/ext/voice_recv/extras/speechrecognition.py
discord_ext_voice_recv-0.5.2a179.dist-info/licenses/LICENSE
discord_ext_voice_recv-0.5.2a179.dist-info/METADATA
discord_ext_voice_recv-0.5.2a179.dist-info/WHEEL
discord_ext_voice_recv-0.5.2a179.dist-info/top_level.txt
discord_ext_voice_recv-0.5.2a179.dist-info/RECORD
