Metadata-Version: 2.4
Name: discord-ext-voice_recv
Version: 0.5.2a179
Summary: Experimental voice receive extension for discord.py
Home-page: https://github.com/imayhaveborkedit/discord-ext-voice-recv
Author: Imayhaveborkedit
License: MIT
Classifier: Development Status :: 3 - Alpha
Classifier: License :: OSI Approved :: MIT License
Classifier: Intended Audience :: Developers
Classifier: Natural Language :: English
Classifier: Programming Language :: Python :: 3.8
Classifier: Programming Language :: Python :: 3.9
Classifier: Programming Language :: Python :: 3.10
Classifier: Programming Language :: Python :: 3.11
Classifier: Programming Language :: Python :: 3.12
Classifier: Operating System :: POSIX
Classifier: Operating System :: Microsoft :: Windows
Classifier: Operating System :: MacOS
Classifier: Topic :: Multimedia :: Sound/Audio :: Capture/Recording
Requires-Python: >=3.8
License-File: LICENSE
Requires-Dist: discord.py[voice]>=2.5
Provides-Extra: extras-speech
Requires-Dist: SpeechRecognition; extra == "extras-speech"
Provides-Extra: extras-local
Requires-Dist: pyaudio; extra == "extras-local"
Provides-Extra: extras
Requires-Dist: SpeechRecognition; extra == "extras"
Requires-Dist: pyaudio; extra == "extras"
Dynamic: author
Dynamic: classifier
Dynamic: description
Dynamic: description-content-type
Dynamic: home-page
Dynamic: license
Dynamic: license-file
Dynamic: provides-extra
Dynamic: requires-dist
Dynamic: requires-python
Dynamic: summary
